bowser/__init__.py
bowser/_prepare_disp_s1.py
bowser/_prepare_nisar.py
bowser/_prepare_utils.py
bowser/_version.py
bowser/cli.py
bowser/config.py
bowser/main.py
bowser/readers.py
bowser/titiler.py
bowser/utils.py
bowser/dist/index.css
bowser/dist/index.html
bowser/dist/index.js
bowser_insar-0.3.0.dist-info/licenses/LICENSE
bowser_insar-0.3.0.dist-info/METADATA
bowser_insar-0.3.0.dist-info/WHEEL
bowser_insar-0.3.0.dist-info/entry_points.txt
bowser_insar-0.3.0.dist-info/top_level.txt
bowser_insar-0.3.0.dist-info/RECORD
