Metadata-Version: 2.4
Name: bowser-insar
Version: 0.3.0
Summary: Web UI for browsing InSAR time series
Author-email: Scott Staniewicz <scott.stanie@gmail.com>
Classifier: Intended Audience :: Developers
Classifier: Intended Audience :: Science/Research
Classifier: Programming Language :: Python :: 3
Classifier: Programming Language :: Python :: 3.10
Classifier: Programming Language :: Python :: 3.11
Classifier: Programming Language :: Python :: 3.12
Classifier: Programming Language :: Python :: 3.13
Classifier: Programming Language :: Python
Classifier: Topic :: Scientific/Engineering
Classifier: Typing :: Typed
Requires-Python: >=3.10
License-File: LICENSE
Requires-Dist: titiler.xarray[http,minimal]
Requires-Dist: starlette-cramjam
Requires-Dist: boto3
Requires-Dist: uvicorn
Requires-Dist: typing_extensions
Requires-Dist: tqdm
Requires-Dist: opera-utils[disp]
Requires-Dist: rioxarray
Requires-Dist: matplotlib
Requires-Dist: pydantic_settings
Provides-Extra: docs
Provides-Extra: test
Requires-Dist: httpx; extra == "test"
Requires-Dist: pytest; extra == "test"
Dynamic: license-file
